elphick/geomet/__init__.py
elphick/geomet/base.py
elphick/geomet/block_model.py
elphick/geomet/config/__init__.py
elphick/geomet/config/config_read.py
elphick/geomet/config/flowsheet_example_partition.yaml
elphick/geomet/config/flowsheet_example_simple.yaml
elphick/geomet/config/mc_config.yml
elphick/geomet/data/downloader.py
elphick/geomet/data/register.csv
elphick/geomet/datasets/__init__.py
elphick/geomet/datasets/datasets.py
elphick/geomet/datasets/downloader.py
elphick/geomet/datasets/register.csv
elphick/geomet/datasets/sample_data.py
elphick/geomet/extras.py
elphick/geomet/flowsheet/__init__.py
elphick/geomet/flowsheet/flowsheet.py
elphick/geomet/flowsheet/loader.py
elphick/geomet/flowsheet/operation.py
elphick/geomet/flowsheet/stream.py
elphick/geomet/interval_sample.py
elphick/geomet/io.py
elphick/geomet/plot.py
elphick/geomet/profile.py
elphick/geomet/sample.py
elphick/geomet/utils/__init__.py
elphick/geomet/utils/amenability.py
elphick/geomet/utils/block_model_converter.py
elphick/geomet/utils/components.py
elphick/geomet/utils/data.py
elphick/geomet/utils/estimates.py
elphick/geomet/utils/interp.py
elphick/geomet/utils/interp2.py
elphick/geomet/utils/layout.py
elphick/geomet/utils/moisture.py
elphick/geomet/utils/pandas.py
elphick/geomet/utils/parallel.py
elphick/geomet/utils/partition.py
elphick/geomet/utils/size.py
elphick/geomet/utils/timer.py
elphick/geomet/utils/viz.py
elphick/geomet/validate.py.hide
geometallurgy-0.4.17.dist-info/LICENSE
geometallurgy-0.4.17.dist-info/METADATA
geometallurgy-0.4.17.dist-info/WHEEL
geometallurgy-0.4.17.dist-info/entry_points.txt
geometallurgy-0.4.17.dist-info/RECORD
