Metadata-Version: 2.1
Name: geometallurgy
Version: 0.4.17
Summary: Tools for the geometallurgist
Home-page: https://github.com/elphick/geometallurgy
Author: Greg
Author-email: 11791585+elphick@users.noreply.github.com
Requires-Python: >=3.10,<3.13
Classifier: Programming Language :: Python :: 3
Classifier: Programming Language :: Python :: 3.10
Classifier: Programming Language :: Python :: 3.11
Provides-Extra: all
Provides-Extra: blockmodel
Provides-Extra: spatial
Provides-Extra: validation
Requires-Dist: folium (>=0.16.0,<0.17.0) ; extra == "spatial"
Requires-Dist: omfpandas (>=0.8.1) ; extra == "blockmodel"
Requires-Dist: omfvista (>=0.3.0) ; extra == "blockmodel"
Requires-Dist: pandas (>=1.0)
Requires-Dist: pandera[io] (>=0.19.3,<0.21.0) ; extra == "validation"
Requires-Dist: periodictable (>=1.7.0,<2.0.0)
Requires-Dist: plotly (>=5.22.0,<6.0.0)
Requires-Dist: pyarrow (>=16.1.0,<18.0.0)
Requires-Dist: rioxarray (>=0.18.2,<0.19.0) ; extra == "spatial"
Project-URL: Documentation, https://elphick.github.io/geometallurgy
Project-URL: Repository, https://github.com/elphick/geometallurgy
